tinyerr/__init__.py
tinyerr/__main__.py
tinyerr/anchor.py
tinyerr/config.py
tinyerr/errors.py
tinyerr/exechook.py
tinyerr/frames.py
tinyerr-0.0.1a2.dist-info/LICENSE
tinyerr-0.0.1a2.dist-info/METADATA
tinyerr-0.0.1a2.dist-info/WHEEL
tinyerr-0.0.1a2.dist-info/entry_points.txt
tinyerr-0.0.1a2.dist-info/top_level.txt
tinyerr-0.0.1a2.dist-info/RECORD
