Metadata-Version: 2.1
Name: tinyerr
Version: 0.0.1a2
Summary: Tiny Errors that remove the clutter
License: MIT License
Project-URL: repository, https://github.com/James-Ansley/tinyerr
Requires-Python: >=3.11
License-File: LICENSE
